{
  "enabled": true,
  "checkIntervalMs": 900000,
  "alerts": {
    "priceChange": {
      "enabled": true,
      "threshold": 5,
      "coins": []
    },
    "rsiExtreme": {
      "enabled": true,
      "overbought": 70,
      "oversold": 30,
      "coins": []
    },
    "volumeSpike": {
      "enabled": true,
      "multiplier": 3,
      "coins": []
    }
  },
  "lastCheck": "2026-03-02T16:47:21.505Z",
  "lastAlerts": [
    {
      "type": "coingecko_signal",
      "coin": "ethena",
      "direction": "LONG",
      "rr": 1.8,
      "entry": 0.113618,
      "tp1": 0.1161,
      "tp2": 0.1233,
      "tp3": 0.1291,
      "sl": 0.1083,
      "confidence": 96
    }
  ]
}